setup.py
mike_probability/Binomialdistribution.py
mike_probability/Gaussiandistribution.py
mike_probability/Generaldistribution.py
mike_probability/__init__.py
mike_probability.egg-info/PKG-INFO
mike_probability.egg-info/SOURCES.txt
mike_probability.egg-info/dependency_links.txt
mike_probability.egg-info/not-zip-safe
mike_probability.egg-info/top_level.txt