Metadata-Version: 1.0
Name: mike-probability
Version: 0.1.93
Summary: Gaussian and Binomial distributions 
Home-page: UNKNOWN
Author: Micheal Akinkuotu
Author-email: michealakinkuotu73@gmail.com
License: UNKNOWN
Platform: UNKNOWN
